sourcescribe/__init__.py
sourcescribe/__main__.py
sourcescribe/cli.py
sourcescribe/api/__init__.py
sourcescribe/api/anthropic_provider.py
sourcescribe/api/base.py
sourcescribe/api/factory.py
sourcescribe/api/ollama_provider.py
sourcescribe/api/openai_provider.py
sourcescribe/config/__init__.py
sourcescribe/config/loader.py
sourcescribe/config/models.py
sourcescribe/engine/__init__.py
sourcescribe/engine/analyzer.py
sourcescribe/engine/diagram.py
sourcescribe/engine/feature_generator.py
sourcescribe/engine/generator.py
sourcescribe/utils/__init__.py
sourcescribe/utils/file_utils.py
sourcescribe/utils/github_utils.py
sourcescribe/utils/logger.py
sourcescribe/utils/parser.py
sourcescribe/watch/__init__.py
sourcescribe/watch/handler.py
sourcescribe/watch/watcher.py
sourcescribe-1.6.2.dist-info/licenses/LICENSE
sourcescribe-1.6.2.dist-info/METADATA
sourcescribe-1.6.2.dist-info/WHEEL
sourcescribe-1.6.2.dist-info/entry_points.txt
sourcescribe-1.6.2.dist-info/top_level.txt
sourcescribe-1.6.2.dist-info/RECORD
